german/__init__.py
german/preprocessing.py
german-0.1.0.dist-info/LICENSE
german-0.1.0.dist-info/METADATA
german-0.1.0.dist-info/WHEEL
german-0.1.0.dist-info/top_level.txt
german-0.1.0.dist-info/RECORD
