Metadata-Version: 2.1
Name: german
Version: 0.1.0
Summary: Preprocess German texts for serious NLP.
Home-page: https://github.com/jfilter/german-preprocessing
Author: Johannes Filter
Author-email: hi@jfilter.de
License: MIT
Platform: UNKNOWN
Classifier: Programming Language :: Python :: 3.6
Classifier: Programming Language :: Python :: 3.7
Classifier: License :: OSI Approved :: MIT License
Classifier: Topic :: Utilities
Requires-Dist: german-lemmatizer
Requires-Dist: clean-text
Requires-Dist: joblib
Requires-Dist: tqdm
Requires-Dist: unidecode
